chart4t/__init__.py
chart4t/common.py
圖表模組/__init__.py
chart4t-0.0.1.dist-info/LICENSE
chart4t-0.0.1.dist-info/METADATA
chart4t-0.0.1.dist-info/WHEEL
chart4t-0.0.1.dist-info/top_level.txt
chart4t-0.0.1.dist-info/RECORD
